laterpay/__init__.py
laterpay/compat.py
laterpay/constants.py
laterpay/signing.py
laterpay/utils.py
laterpay_client-5.9.0.dist-info/DESCRIPTION.rst
laterpay_client-5.9.0.dist-info/METADATA
laterpay_client-5.9.0.dist-info/RECORD
laterpay_client-5.9.0.dist-info/WHEEL
laterpay_client-5.9.0.dist-info/metadata.json
laterpay_client-5.9.0.dist-info/top_level.txt
