Metadata-Version: 2.0
Name: laterpay-client
Version: 5.9.0
Summary: LaterPay API client
Home-page: https://github.com/laterpay/laterpay-client-python
Author: LaterPay GmbH
Author-email: support@laterpay.net
License: MIT
Keywords: LaterPay API client
Platform: UNKNOWN
Classifier: Development Status :: 5 - Production/Stable
Classifier: Intended Audience :: Developers
Classifier: License :: OSI Approved :: MIT License
Classifier: Operating System :: OS Independent
Classifier: Programming Language :: Python
Classifier: Programming Language :: Python :: 2
Classifier: Programming Language :: Python :: 2.7
Classifier: Programming Language :: Python :: 3
Classifier: Programming Language :: Python :: 3.3
Classifier: Programming Language :: Python :: 3.4
Classifier: Programming Language :: Python :: 3.5
Classifier: Programming Language :: Python :: 3.6
Classifier: Topic :: Software Development :: Libraries :: Python Modules
Requires-Dist: PyJWT (>=1.4.2)
Requires-Dist: requests
Requires-Dist: six
